setup.cfg
setup.py
bin/hallgrim
hallgrim/MultipartEncoder.py
hallgrim/__init__.py
hallgrim/custom_markdown.py
hallgrim/hallgrim.py
hallgrim/messages.py
hallgrim/parser.py
hallgrim/templates.py
hallgrim/uploader.py
hallgrim.egg-info/PKG-INFO
hallgrim.egg-info/SOURCES.txt
hallgrim.egg-info/dependency_links.txt
hallgrim.egg-info/requires.txt
hallgrim.egg-info/top_level.txt
hallgrim/IliasXMLCreator/__init__.py
hallgrim/IliasXMLCreator/abstract_question.py
hallgrim/IliasXMLCreator/free.py
hallgrim/IliasXMLCreator/gap.py
hallgrim/IliasXMLCreator/multi.py
hallgrim/IliasXMLCreator/order.py
hallgrim/IliasXMLCreator/packer.py
hallgrim/IliasXMLCreator/single.py
hallgrim/IliasXMLCreator/xmlBuildingBlocks.py