Metadata-Version: 1.1
Name: hallgrim
Version: 0.4.0
Summary: A script generator for the ILIAS platform
Home-page: https://gitlab.gwdg.de/j.michal/ilias-generator
Author: Jan Maximilian Michal
Author-email: mail-github@jmx.io
License: MIT
Download-URL: https://gitlab.gwdg.de/j.michal/ilias-generator/repository/archive.tar.gz?ref=0.4.0
Platform: UNKNOWN
